chromaprint/__init__.py
chromaprint/chromaprint.py
chromaprint-0.5.dist-info/METADATA
chromaprint-0.5.dist-info/RECORD
chromaprint-0.5.dist-info/WHEEL
chromaprint-0.5.dist-info/top_level.txt
