Metadata-Version: 2.1
Name: chromaprint
Version: 0.5
Summary: Small package to facilitate colored terminal output.
Home-page: https://github.com/nosmokingbandit/chromaprint
Author: NoSmokingBandit
Author-email: nosmokingbandit@gmail.com
License: UNKNOWN
Platform: UNKNOWN
Classifier: Programming Language :: Python :: 3
Classifier: License :: OSI Approved :: MIT License
Classifier: Operating System :: OS Independent
